limecore/messaging/api/__init__.py
limecore/messaging/api/app.py
limecore/messaging/api/app_factory.py
limecore/messaging/api/handler.py
limecore/messaging/api/message.py
limecore/messaging/api/publisher.py
limecore/messaging/api/subscriber.py
limecore/messaging/api/subscription.py
limecore/messaging/api/subscription_builder.py
limecore/messaging/api/worker.py
limecore/messaging/api/serialization/__init__.py
limecore/messaging/api/serialization/json/__init__.py
limecore/messaging/api/serialization/json/json_decoder.py
limecore/messaging/api/serialization/json/json_encoder.py
limecore/messaging/api/serialization/json/serializers/__init__.py
limecore/messaging/api/serialization/json/serializers/base_serializer.py
limecore/messaging/api/serialization/json/serializers/generic_serializer.py
limecore/messaging/api/serialization/json/serializers/serializer.py
limecore/messaging/api/serialization/json/serializers/uuid_serializer.py
limecore_messaging_api-0.2.1.dist-info/LICENSE.txt
limecore_messaging_api-0.2.1.dist-info/METADATA
limecore_messaging_api-0.2.1.dist-info/WHEEL
limecore_messaging_api-0.2.1.dist-info/top_level.txt
limecore_messaging_api-0.2.1.dist-info/RECORD
